{
  "name": "Menu Floating Action Button",
  "alias": "Menu FAB",
  "description": "",
  "thumbnail": "./thumbnail.png",
  "primitive": "../../primitive/button/primitive-meta.json",
  "group": "FAB",
  "platform": {
    "ios": {
      "status": "in-progress",
      "alias": "",
      "path": ""
    },
    "android": {
      "status": "todo",
      "path": ""
    },
    "react": {
      "status": "done",
      "path": "https://sprout-storybook.vercel.app/?path=/docs/components-fab-menufab--docs"
    },
    "figma": {
      "status": "todo",
      "path": ""
    },
    "docs": {
      "overview": {
        "status": "in-progress",
        "mdx": "./overview.mdx"
      },
      "usage": {
        "status": "in-progress",
        "mdx": "./usage.mdx"
      },
      "style": {
        "status": "done",
        "mdx": "./style.mdx"
      }
    }
  }
}
